MANIFEST.in
README
setup.cfg
setup.py
pybb/__init__.py
pybb/admin.py
pybb/export.py
pybb/feeds.py
pybb/forms.py
pybb/middleware.py
pybb/models.py
pybb/read_tracking.py
pybb/settings.py
pybb/signals.py
pybb/subscription.py
pybb/tests.py
pybb/urls.py
pybb/util.py
pybb/views.py
pybb.egg-info/PKG-INFO
pybb.egg-info/SOURCES.txt
pybb.egg-info/dependency_links.txt
pybb.egg-info/requires.txt
pybb.egg-info/top_level.txt
pybb/management/__init__.py
pybb/management/commands/__init__.py
pybb/management/commands/pybb_create_related_objects.py
pybb/management/commands/pybb_delete_invalid_topics.py
pybb/management/commands/pybb_install.py
pybb/management/commands/pybb_manage_supermoderator.py
pybb/management/commands/pybb_rebuild_counters.py
pybb/markups/__init__.py
pybb/markups/mypostmarkup.py
pybb/markups/postmarkup.py
pybb/migrations/0001_initial.py
pybb/migrations/__init__.py
pybb/static/pybb/css/style.css
pybb/static/pybb/img/anonymous.gif
pybb/static/pybb/js/pybbjs.js
pybb/templates/pybb/_category_row.html
pybb/templates/pybb/_forum_row.html
pybb/templates/pybb/_post_row.html
pybb/templates/pybb/_topic_mini_pagination.html
pybb/templates/pybb/base.html
pybb/templates/pybb/category_details.html
pybb/templates/pybb/forum_details.html
pybb/templates/pybb/index.html
pybb/templates/pybb/last_topics.html
pybb/templates/pybb/pagination.html
pybb/templates/pybb/post_add.html
pybb/templates/pybb/post_delete.html
pybb/templates/pybb/post_edit.html
pybb/templates/pybb/post_form.html
pybb/templates/pybb/profile_edit.html
pybb/templates/pybb/topic_details.html
pybb/templates/pybb/topic_merge.html
pybb/templates/pybb/user_details.html
pybb/templates/pybb/user_details_posts.html
pybb/templates/pybb/user_details_topics.html
pybb/templates/pybb/user_list.html
pybb/templates/pybb/feeds/forum_post_description.html
pybb/templates/pybb/feeds/forum_post_title.html
pybb/templates/pybb/feeds/posts_description.html
pybb/templates/pybb/feeds/posts_title.html
pybb/templates/pybb/feeds/topics_description.html
pybb/templates/pybb/feeds/topics_title.html
pybb/templatetags/__init__.py
pybb/templatetags/pybb_tags.py