Metadata-Version: 1.0
Name: pybb
Version: 0.1.10
Summary: Django forum application
Home-page: http://pybb.org
Author: Grigoriy Petukhov
Author-email: lorien@lorien.name
License: BSD
Keywords: django application forum board
Platform: UNKNOWN
Classifier: Development Status :: 4 - Beta
Classifier: Environment :: Web Environment
Classifier: Framework :: Django
Classifier: Intended Audience :: Developers
Classifier: License :: OSI Approved :: BSD License
Classifier: Operating System :: OS Independent
Classifier: Programming Language :: Python
Classifier: Topic :: Internet :: WWW/HTTP :: Dynamic Content :: Message Boards
Classifier: Topic :: Software Development :: Libraries :: Python Modules
